{
  "steps": [
    {
      "id": "P1",
      "type": "ground",
      "x": -487,
      "y": 0
    },
    {
      "id": "P2",
      "type": "input_linear",
      "p1": "P1",
      "ux": 1,
      "uy": 0,
      "baseLen": 100,
      "len_param": "L1",
      "maxStroke": 50,
      "valve_id": "1",
      "physical_motor": "1"
    },
    {
      "id": "H1",
      "type": "point_on_link",
      "p1": "P3",
      "p2": "P4",
      "dist_param": "H1_dist"
    },
    {
      "id": "P3",
      "type": "joint",
      "x": -202.356936106102,
      "y": 98.71730660396722
    },
    {
      "id": "P4",
      "type": "joint",
      "x": -116,
      "y": -115
    }
  ],
  "tracePoint": "P1",
  "visualization": {
    "links": [
      {
        "id": "Link1_piston",
        "p1": "P1",
        "p2": "P2",
        "color": "#3498db",
        "style": "piston",
        "tubeLen": 100
      },
      {
        "id": "Link2",
        "p1": "P2",
        "p2": "P3",
        "color": "#3498db",
        "style": "normal",
        "lenParam": "L2",
        "hidden": false
      },
      {
        "id": "Link3",
        "p1": "P3",
        "p2": "P4",
        "color": "#3498db",
        "style": "normal",
        "lenParam": "L3",
        "hidden": false
      }
    ],
    "polygons": [],
    "joints": [
      "P1",
      "P2",
      "H1",
      "P3",
      "P4"
    ]
  },
  "parts": [
    {
      "id": "Link1(L1)",
      "type": "bar",
      "len_param": "L1",
      "color": "#3498db",
      "isInput": true,
      "holes": []
    },
    {
      "id": "Link2(L2)",
      "type": "bar",
      "len_param": "L2",
      "color": "#3498db",
      "isInput": false,
      "holes": []
    },
    {
      "id": "Link3(L3)",
      "type": "bar",
      "len_param": "L3",
      "color": "#3498db",
      "isInput": false,
      "holes": [
        {
          "id": "H1",
          "dist_param": "H1_dist"
        }
      ]
    }
  ],
  "params": {
    "L1": 160,
    "L2": 159,
    "L3": 231,
    "H1_dist": 121
  },
  "_wizard_data": [
    {
      "type": "bar",
      "id": "Link1",
      "color": "#3498db",
      "p1": {
        "id": "P1",
        "type": "linear",
        "x": -487,
        "y": 0
      },
      "p2": {
        "id": "P2",
        "type": "floating",
        "x": -327,
        "y": 0
      },
      "lenParam": "L1",
      "isInput": true,
      "phaseOffset": 0,
      "style": "piston",
      "tubeLen": 100,
      "maxStroke": 50,
      "physicalMotor": "1"
    },
    {
      "type": "bar",
      "id": "Link2",
      "color": "#3498db",
      "p1": {
        "id": "P2",
        "type": "existing",
        "x": -327,
        "y": 0
      },
      "p2": {
        "id": "P3",
        "type": "floating",
        "x": -202,
        "y": 99
      },
      "lenParam": "L2",
      "isInput": false
    },
    {
      "type": "bar",
      "id": "Link3",
      "color": "#3498db",
      "p1": {
        "id": "P3",
        "type": "existing",
        "x": -202.356936106102,
        "y": 98.71730660396722
      },
      "p2": {
        "id": "P4",
        "type": "floating",
        "x": -116,
        "y": -115
      },
      "lenParam": "L3",
      "isInput": false,
      "holes": [
        {
          "id": "H1",
          "distParam": "H1_dist"
        }
      ]
    }
  ]
}
